pysidra/__init__.py
pysidra/api/__init__.py
pysidra/api/auth/__init__.py
pysidra/api/auth/authentication.py
pysidra/api/client/__init__.py
pysidra/api/client/client.py
pysidra/api/controllers/__init__.py
pysidra/api/controllers/constants.py
pysidra/api/controllers/controllers.py
pysidra/api/controllers/util.py
pysidra/api/controllers/datacatalog/__init__.py
pysidra/api/controllers/datacatalog/attributes.py
pysidra/api/controllers/datacatalog/datastorageunit.py
pysidra/api/controllers/datacatalog/entities.py
pysidra/api/controllers/datacatalog/providers.py
pysidra/api/controllers/datacatalog/storageroles.py
pysidra/api/controllers/datacatalog/storages.py
pysidra/api/controllers/datacatalog/tags.py
pysidra/api/controllers/integration/__init__.py
pysidra/api/controllers/integration/inference.py
pysidra/api/controllers/integration/query.py
pysidra/api/controllers/modelserving/__init__.py
pysidra/api/controllers/modelserving/common.py
pysidra/api/controllers/modelserving/model.py
pysidra/api/controllers/modelserving/modelversion.py
pysidra/api/controllers/operations/__init__.py
pysidra/api/controllers/operations/assets.py
pysidra/api/controllers/operations/assetstatus.py
pysidra/api/controllers/operations/service.py
pysidra/api/models/__init__.py
pysidra/api/models/common/__init__.py
pysidra/api/models/common/dict_utils.py
pysidra/api/models/common/pagination.py
pysidra/api/models/modelserving/__init__.py
pysidra/api/models/modelserving/model.py
pysidra/api/models/modelserving/modelversion.py
pySidra-1.12.0.dist-info/LICENSE
pySidra-1.12.0.dist-info/METADATA
pySidra-1.12.0.dist-info/WHEEL
pySidra-1.12.0.dist-info/top_level.txt
pySidra-1.12.0.dist-info/RECORD
